valaya/__init__.py
valaya/config.toml
valaya/valaya.py
valaya/valaya_cli.py
valaya-0.0.11.dist-info/LICENSE
valaya-0.0.11.dist-info/METADATA
valaya-0.0.11.dist-info/WHEEL
valaya-0.0.11.dist-info/entry_points.txt
valaya-0.0.11.dist-info/top_level.txt
valaya-0.0.11.dist-info/RECORD
