Metadata-Version: 2.1
Name: valaya
Version: 0.0.11
Summary: A secure and customizable cloud storage system built with an open source client.
Author-email: Sakshine <sakshine108@gmail.com>
License: MIT License
Project-URL: Repository, https://github.com/sakshine108/valaya
Requires-Python: >=3.8
License-File: LICENSE
Requires-Dist: cryptography ==41.0.5
Requires-Dist: humanize ==4.9.0
Requires-Dist: munch ==4.0.0
Requires-Dist: outdated ==0.2.2
Requires-Dist: pathvalidate ==3.2.0
Requires-Dist: pwinput ==1.0.3
Requires-Dist: setuptools ==66.1.1
Requires-Dist: toml ==0.10.2
Requires-Dist: tqdm ==4.66.1
